pytauri/__init__.py
pytauri/_gen_ts.py
pytauri/image.py
pytauri/ipc.py
pytauri/menu.py
pytauri/path.py
pytauri/plugin.py
pytauri/py.typed
pytauri/tray.py
pytauri/webview.py
pytauri/window.py
pytauri/ffi/__init__.py
pytauri/ffi/_ext_mod.py
pytauri/ffi/_typing.py
pytauri/ffi/image.py
pytauri/ffi/ipc.py
pytauri/ffi/lib.py
pytauri/ffi/menu.py
pytauri/ffi/path.py
pytauri/ffi/plugin.py
pytauri/ffi/tray.py
pytauri/ffi/webview.py
pytauri/ffi/window.py
pytauri_plugins/__init__.py
pytauri_plugins/py.typed
pytauri_plugins/autostart/__init__.py
pytauri_plugins/autostart/ffi.py
pytauri_plugins/clipboard_manager/__init__.py
pytauri_plugins/clipboard_manager/ffi.py
pytauri_plugins/deep_link/__init__.py
pytauri_plugins/deep_link/ffi.py
pytauri_plugins/dialog/__init__.py
pytauri_plugins/dialog/ffi.py
pytauri_plugins/fs/__init__.py
pytauri_plugins/fs/ffi.py
pytauri_plugins/global_shortcut/__init__.py
pytauri_plugins/global_shortcut/ffi.py
pytauri_plugins/http/__init__.py
pytauri_plugins/http/ffi.py
pytauri_plugins/notification/__init__.py
pytauri_plugins/notification/ffi.py
pytauri_plugins/opener/__init__.py
pytauri_plugins/opener/ffi.py
pytauri_plugins/os/__init__.py
pytauri_plugins/os/ffi.py
pytauri_plugins/persisted_scope/__init__.py
pytauri_plugins/persisted_scope/ffi.py
pytauri_plugins/positioner/__init__.py
pytauri_plugins/positioner/ffi.py
pytauri_plugins/process/__init__.py
pytauri_plugins/process/ffi.py
pytauri_plugins/shell/__init__.py
pytauri_plugins/shell/ffi.py
pytauri_plugins/single_instance/__init__.py
pytauri_plugins/single_instance/ffi.py
pytauri_plugins/updater/__init__.py
pytauri_plugins/updater/ffi.py
pytauri_plugins/upload/__init__.py
pytauri_plugins/upload/ffi.py
pytauri_plugins/websocket/__init__.py
pytauri_plugins/websocket/ffi.py
pytauri_plugins/window_state/__init__.py
pytauri_plugins/window_state/ffi.py
pytauri_utils/__init__.py
pytauri_utils/py.typed
pytauri_utils/async_tools/__init__.py
pytauri-0.8.0.dist-info/METADATA
pytauri-0.8.0.dist-info/WHEEL
pytauri-0.8.0.dist-info/RECORD
