Metadata-Version: 2.4
Name: pytauri
Version: 0.8.0
Summary: Tauri binding for Python through Pyo3.
Project-URL: documentation, https://pytauri.github.io/pytauri/
Project-URL: source, https://github.com/pytauri/pytauri
Author-email: Sean Wang <126865849+WSH032@users.noreply.github.com>
License-Expression: Apache-2.0
Requires-Python: >=3.9
Requires-Dist: anyio>=4
Requires-Dist: importlib-metadata>=8
Requires-Dist: pillow>=11.1
Requires-Dist: pydantic>=2
Requires-Dist: typing-extensions>=4.14
